[{"city":"Ardabil","state":"Ardabil","country":"Iran"},{"city":"Garmi","state":"Ardabil","country":"Iran"},{"city":"Khalkhal","state":"Ardabil","country":"Iran"},{"city":"Meshkinshahr","state":"Ardabil","country":"Iran"},{"city":"Parsabad","state":"Ardabil","country":"Iran"},{"city":"Bandar-e Gonaveh","state":"Bushehr","country":"Iran"},{"city":"Borazjan","state":"Bushehr","country":"Iran"},{"city":"Bushehr","state":"Bushehr","country":"Iran"},{"city":"Dashti","state":"Bushehr","country":"Iran"},{"city":"Dir","state":"Bushehr","country":"Iran"},{"city":"Khormuj","state":"Bushehr","country":"Iran"},{"city":"Kongan","state":"Bushehr","country":"Iran"},{"city":"Tangestan","state":"Bushehr","country":"Iran"},{"city":"Ardistan","state":"Esfahan","country":"Iran"},{"city":"Dorchehpiyaz","state":"Esfahan","country":"Iran"},{"city":"Dowlatabad","state":"Esfahan","country":"Iran"},{"city":"Esfahan","state":"Esfahan","country":"Iran"},{"city":"Falavarjan","state":"Esfahan","country":"Iran"},{"city":"Faridan","state":"Esfahan","country":"Iran"},{"city":"Fereydunshahr","state":"Esfahan","country":"Iran"},{"city":"Fuladshahr","state":"Esfahan","country":"Iran"},{"city":"Golara","state":"Esfahan","country":"Iran"},{"city":"Golpayegan","state":"Esfahan","country":"Iran"},{"city":"Kashan","state":"Esfahan","country":"Iran"},{"city":"Kelishad","state":"Esfahan","country":"Iran"},{"city":"Khomeynishahr","state":"Esfahan","country":"Iran"},{"city":"Khonsar","state":"Esfahan","country":"Iran"},{"city":"Khuresgan","state":"Esfahan","country":"Iran"},{"city":"Mobarakeh","state":"Esfahan","country":"Iran"},{"city":"Na'in","state":"Esfahan","country":"Iran"},{"city":"Najafabad","state":"Esfahan","country":"Iran"},{"city":"Natnaz","state":"Esfahan","country":"Iran"},{"city":"Qahdarijan","state":"Esfahan","country":"Iran"},{"city":"Rehnan","state":"Esfahan","country":"Iran"},{"city":"Semirom","state":"Esfahan","country":"Iran"},{"city":"Shahinshahr","state":"Esfahan","country":"Iran"},{"city":"Shahreza","state":"Esfahan","country":"Iran"},{"city":"Zarinshahr","state":"Esfahan","country":"Iran"},{"city":"Abadeh","state":"Fars","country":"Iran"},{"city":"Akbarabad","state":"Fars","country":"Iran"},{"city":"Darab","state":"Fars","country":"Iran"},{"city":"Eqlid","state":"Fars","country":"Iran"},{"city":"Estehban","state":"Fars","country":"Iran"},{"city":"Fasa","state":"Fars","country":"Iran"},{"city":"Firuzabad","state":"Fars","country":"Iran"},{"city":"Gerash","state":"Fars","country":"Iran"},{"city":"Jahrom","state":"Fars","country":"Iran"},{"city":"Kazerun","state":"Fars","country":"Iran"},{"city":"Lar","state":"Fars","country":"Iran"},{"city":"Marv Dasht","state":"Fars","country":"Iran"},{"city":"Neyriz","state":"Fars","country":"Iran"},{"city":"Nurabad","state":"Fars","country":"Iran"},{"city":"Qa'emiyeh","state":"Fars","country":"Iran"},{"city":"Sepidan","state":"Fars","country":"Iran"},{"city":"Shiraz","state":"Fars","country":"Iran"},{"city":"Astaneh-ye Ashrafiyeh","state":"Gilan","country":"Iran"},{"city":"Astara","state":"Gilan","country":"Iran"},{"city":"Bandar-e Anzali","state":"Gilan","country":"Iran"},{"city":"Faman","state":"Gilan","country":"Iran"},{"city":"Hashtpar","state":"Gilan","country":"Iran"},{"city":"Lahijan","state":"Gilan","country":"Iran"},{"city":"Langarud","state":"Gilan","country":"Iran"},{"city":"Rasht","state":"Gilan","country":"Iran"},{"city":"Rudbar","state":"Gilan","country":"Iran"},{"city":"Rudsar","state":"Gilan","country":"Iran"},{"city":"Sawma'eh Sara","state":"Gilan","country":"Iran"},{"city":"Aq Qal'eh","state":"Golestan","country":"Iran"},{"city":"Azad Shahr","state":"Golestan","country":"Iran"},{"city":"Bandar-e Torkaman","state":"Golestan","country":"Iran"},{"city":"Gonbad-e Qabus","state":"Golestan","country":"Iran"},{"city":"Gorgan","state":"Golestan","country":"Iran"},{"city":"Asadabad","state":"Hamadan","country":"Iran"},{"city":"Bahar","state":"Hamadan","country":"Iran"},{"city":"Hamadan","state":"Hamadan","country":"Iran"},{"city":"Malayer","state":"Hamadan","country":"Iran"},{"city":"Nahavand","state":"Hamadan","country":"Iran"},{"city":"Tuysarkan","state":"Hamadan","country":"Iran"},{"city":"Bandar Abbas","state":"Hormozgan","country":"Iran"},{"city":"Bandar-e 'Abbas","state":"Hormozgan","country":"Iran"},{"city":"Bandar-e Lengeh","state":"Hormozgan","country":"Iran"},{"city":"Gheshm","state":"Hormozgan","country":"Iran"},{"city":"Jask","state":"Hormozgan","country":"Iran"},{"city":"Kish","state":"Hormozgan","country":"Iran"},{"city":"Kish Island","state":"Hormozgan","country":"Iran"},{"city":"Minab","state":"Hormozgan","country":"Iran"},{"city":"Abdanan","state":"Ilam","country":"Iran"},{"city":"Darrehshahr","state":"Ilam","country":"Iran"},{"city":"Dehloran","state":"Ilam","country":"Iran"},{"city":"Ilam","state":"Ilam","country":"Iran"},{"city":"Ivan","state":"Ilam","country":"Iran"},{"city":"Mehran","state":"Ilam","country":"Iran"},{"city":"Baft","state":"Kerman","country":"Iran"},{"city":"Bam","state":"Kerman","country":"Iran"},{"city":"Bardsir","state":"Kerman","country":"Iran"},{"city":"Jiroft","state":"Kerman","country":"Iran"},{"city":"Kahnuj","state":"Kerman","country":"Iran"},{"city":"Kerman","state":"Kerman","country":"Iran"},{"city":"Rafsanjan","state":"Kerman","country":"Iran"},{"city":"Ravar","state":"Kerman","country":"Iran"},{"city":"Shahr-e Babak","state":"Kerman","country":"Iran"},{"city":"Sirjan","state":"Kerman","country":"Iran"},{"city":"Zarand","state":"Kerman","country":"Iran"},{"city":"Eslamabad","state":"Kermanshah","country":"Iran"},{"city":"Gilan-e Garb","state":"Kermanshah","country":"Iran"},{"city":"Harsin","state":"Kermanshah","country":"Iran"},{"city":"Javanrud","state":"Kermanshah","country":"Iran"},{"city":"Kangavar","state":"Kermanshah","country":"Iran"},{"city":"Kermanshah","state":"Kermanshah","country":"Iran"},{"city":"Paveh","state":"Kermanshah","country":"Iran"},{"city":"Sahneh","state":"Kermanshah","country":"Iran"},{"city":"Sar-e-Pol-e-Zohab","state":"Kermanshah","country":"Iran"},{"city":"Sonqor","state":"Kermanshah","country":"Iran"},{"city":"Birjand","state":"Khorasan","country":"Iran"},{"city":"Bojnurd","state":"Khorasan","country":"Iran"},{"city":"Chenaran","state":"Khorasan","country":"Iran"},{"city":"Darreh Gaz","state":"Khorasan","country":"Iran"},{"city":"Esfarayen","state":"Khorasan","country":"Iran"},{"city":"Fariman","state":"Khorasan","country":"Iran"},{"city":"Ferdus","state":"Khorasan","country":"Iran"},{"city":"Gha'nat","state":"Khorasan","country":"Iran"},{"city":"Gonabad","state":"Khorasan","country":"Iran"},{"city":"Kashmar","state":"Khorasan","country":"Iran"},{"city":"Mashad","state":"Khorasan","country":"Iran"},{"city":"Mashhad","state":"Khorasan","country":"Iran"},{"city":"Neyshabur","state":"Khorasan","country":"Iran"},{"city":"Qayen","state":"Khorasan","country":"Iran"},{"city":"Quchan","state":"Khorasan","country":"Iran"},{"city":"Sabzevar","state":"Khorasan","country":"Iran"},{"city":"Sarakhs","state":"Khorasan","country":"Iran"},{"city":"Shirvan","state":"Khorasan","country":"Iran"},{"city":"Tabas","state":"Khorasan","country":"Iran"},{"city":"Tayyebat","state":"Khorasan","country":"Iran"},{"city":"Torbat-e Heydariyeh","state":"Khorasan","country":"Iran"},{"city":"Torbat-e Jam","state":"Khorasan","country":"Iran"},{"city":"Abadan","state":"Khuzestan","country":"Iran"},{"city":"Agha Jari","state":"Khuzestan","country":"Iran"},{"city":"Ahvaz","state":"Khuzestan","country":"Iran"},{"city":"Ahwaz","state":"Khuzestan","country":"Iran"},{"city":"Andimeshk","state":"Khuzestan","country":"Iran"},{"city":"Bandar-e Emam Khomeyni","state":"Khuzestan","country":"Iran"},{"city":"Bandar-e Mahshahr","state":"Khuzestan","country":"Iran"},{"city":"Behbahan","state":"Khuzestan","country":"Iran"},{"city":"Dezful","state":"Khuzestan","country":"Iran"},{"city":"Ezeh","state":"Khuzestan","country":"Iran"},{"city":"Hendijan","state":"Khuzestan","country":"Iran"},{"city":"Khorramshahr","state":"Khuzestan","country":"Iran"},{"city":"Masjed-e Soleyman","state":"Khuzestan","country":"Iran"},{"city":"Omidiyeh","state":"Khuzestan","country":"Iran"},{"city":"Ramhormoz","state":"Khuzestan","country":"Iran"},{"city":"Ramshir","state":"Khuzestan","country":"Iran"},{"city":"Shadegan","state":"Khuzestan","country":"Iran"},{"city":"Shush","state":"Khuzestan","country":"Iran"},{"city":"Shushtar","state":"Khuzestan","country":"Iran"},{"city":"Susangerd","state":"Khuzestan","country":"Iran"},{"city":"Baneh","state":"Kordestan","country":"Iran"},{"city":"Bijar","state":"Kordestan","country":"Iran"},{"city":"Kamyaran","state":"Kordestan","country":"Iran"},{"city":"Marivan","state":"Kordestan","country":"Iran"},{"city":"Qorveh","state":"Kordestan","country":"Iran"},{"city":"Sanandaj","state":"Kordestan","country":"Iran"},{"city":"Saqqez","state":"Kordestan","country":"Iran"},{"city":"Alashtar","state":"Lorestan","country":"Iran"},{"city":"Aligudarz","state":"Lorestan","country":"Iran"},{"city":"Azna","state":"Lorestan","country":"Iran"},{"city":"Borujerd","state":"Lorestan","country":"Iran"},{"city":"Do Rud","state":"Lorestan","country":"Iran"},{"city":"Khorramabad","state":"Lorestan","country":"Iran"},{"city":"Kuhdasht","state":"Lorestan","country":"Iran"},{"city":"Nurabad","state":"Lorestan","country":"Iran"},{"city":"Arak","state":"Markazi","country":"Iran"},{"city":"Ashtian","state":"Markazi","country":"Iran"},{"city":"Delijan","state":"Markazi","country":"Iran"},{"city":"Khomeyn","state":"Markazi","country":"Iran"},{"city":"Mahallat","state":"Markazi","country":"Iran"},{"city":"Sarband","state":"Markazi","country":"Iran"},{"city":"Saveh","state":"Markazi","country":"Iran"},{"city":"Tafresh","state":"Markazi","country":"Iran"},{"city":"Aliabad","state":"Mazandaran","country":"Iran"},{"city":"Amir Kala","state":"Mazandaran","country":"Iran"},{"city":"Amol","state":"Mazandaran","country":"Iran"},{"city":"Babol","state":"Mazandaran","country":"Iran"},{"city":"Babol Sar","state":"Mazandaran","country":"Iran"},{"city":"Behshahr","state":"Mazandaran","country":"Iran"},{"city":"Chalus","state":"Mazandaran","country":"Iran"},{"city":"Fereydunkenar","state":"Mazandaran","country":"Iran"},{"city":"Juybar","state":"Mazandaran","country":"Iran"},{"city":"Kalaleh","state":"Mazandaran","country":"Iran"},{"city":"Kordkuy","state":"Mazandaran","country":"Iran"},{"city":"Mahmudabad","state":"Mazandaran","country":"Iran"},{"city":"Minudasht","state":"Mazandaran","country":"Iran"},{"city":"Neka","state":"Mazandaran","country":"Iran"},{"city":"Nur","state":"Mazandaran","country":"Iran"},{"city":"Nushahr","state":"Mazandaran","country":"Iran"},{"city":"Qa'emshahr","state":"Mazandaran","country":"Iran"},{"city":"Ramsar","state":"Mazandaran","country":"Iran"},{"city":"Sari","state":"Mazandaran","country":"Iran"},{"city":"Savadkuh","state":"Mazandaran","country":"Iran"},{"city":"Tonekabon","state":"Mazandaran","country":"Iran"},{"city":"Abhar","state":"Qazvin","country":"Iran"},{"city":"Abyek","state":"Qazvin","country":"Iran"},{"city":"Qazvin","state":"Qazvin","country":"Iran"},{"city":"Takestan","state":"Qazvin","country":"Iran"},{"city":"Qom","state":"Qom","country":"Iran"},{"city":"Damghan","state":"Semnan","country":"Iran"},{"city":"Garmsar","state":"Semnan","country":"Iran"},{"city":"Semnan","state":"Semnan","country":"Iran"},{"city":"Shahrud","state":"Semnan","country":"Iran"},{"city":"Damavand","state":"Tehran","country":"Iran"},{"city":"Eqbaliyeh","state":"Tehran","country":"Iran"},{"city":"Eslamshahr","state":"Tehran","country":"Iran"},{"city":"Hashtgerd","state":"Tehran","country":"Iran"},{"city":"Karaj","state":"Tehran","country":"Iran"},{"city":"Mahdasht","state":"Tehran","country":"Iran"},{"city":"Malard","state":"Tehran","country":"Iran"},{"city":"Mohammadiyeh","state":"Tehran","country":"Iran"},{"city":"Nazarabad","state":"Tehran","country":"Iran"},{"city":"Pakdasht","state":"Tehran","country":"Iran"},{"city":"Pishva","state":"Tehran","country":"Iran"},{"city":"Qarchak","state":"Tehran","country":"Iran"},{"city":"Qods","state":"Tehran","country":"Iran"},{"city":"Robat Karim","state":"Tehran","country":"Iran"},{"city":"Shahriyar","state":"Tehran","country":"Iran"},{"city":"Tehran","state":"Tehran","country":"Iran"},{"city":"Varamin","state":"Tehran","country":"Iran"},{"city":"Ardakan","state":"Yazd","country":"Iran"},{"city":"Bafq","state":"Yazd","country":"Iran"},{"city":"Mehriz","state":"Yazd","country":"Iran"},{"city":"Meybod","state":"Yazd","country":"Iran"},{"city":"Taft","state":"Yazd","country":"Iran"},{"city":"Yazd","state":"Yazd","country":"Iran"},{"city":"Alvand","state":"Zanjan","country":"Iran"},{"city":"Khorramdarreh","state":"Zanjan","country":"Iran"},{"city":"Zanjan","state":"Zanjan","country":"Iran"}]