{"name_ru": "\u0417\u0438\u043c\u0431\u0430\u0431\u0432\u0435\n", "name_uk": "\u0417\u0456\u043c\u0431\u0430\u0431\u0432\u0435", "name_en": "Zimbabwe", "alias": "zimbabwe", "city": [{"name_ru": "\u0411\u0443\u043b\u0430\u0432\u0430\u0439\u043e", "name_uk": "\u0411\u0443\u043b\u0430\u0432\u0430\u0439\u043e", "name_en": "Bulawayo", "region_ru": "\u0411\u0443\u043b\u0430\u0432\u0430\u0439\u043e", "region_uk": "\u0411\u0443\u043b\u0430\u0432\u0430\u0439\u043e", "region_en": "Bulawayo", "alias": "bulawayo", "country_alias": "zimbabwe"}, {"name_ru": "\u0427\u0438\u0442\u0443\u043d\u0433\u0432\u0438\u0437\u0430", "name_uk": "\u0427\u0438\u0442\u0443\u043d\u0433\u0432\u0456\u0437\u0430", "name_en": "Chitungwiza", "region_ru": "\u0425\u0430\u0440\u0430\u0440\u0435", "region_uk": "\u0425\u0430\u0440\u0430\u0440\u0435", "region_en": "Harare", "alias": "chitungwiza", "country_alias": "zimbabwe"}, {"name_ru": "\u0425\u0430\u0440\u0430\u0440\u0435", "name_uk": "\u0425\u0430\u0440\u0430\u0440\u0435", "name_en": "Harare", "region_ru": "\u0425\u0430\u0440\u0430\u0440\u0435", "region_uk": "\u0425\u0430\u0440\u0430\u0440\u0435", "region_en": "Harare", "alias": "harare", "country_alias": "zimbabwe"}, {"name_ru": "\u0427\u0438\u043c\u0430\u043d\u0438\u043c\u0430\u043d\u0438", "name_uk": "\u0427\u0456\u043c\u0430\u043d\u0456\u043c\u0430\u043d\u0456", "name_en": "Chimanimani", "region_ru": "\u041c\u0430\u043d\u0438\u043a\u0430\u043b\u0435\u043d\u0434", "region_uk": "\u041c\u0430\u043d\u0456\u043a\u0430\u043b\u0435\u043d\u0434", "region_en": "Manicaland", "alias": "chimanimani", "country_alias": "zimbabwe"}, {"name_ru": "\u0427\u0438\u043f\u0438\u043d\u0433\u0435", "name_uk": "\u0427\u0456\u043f\u0456\u043d\u0433", "name_en": "Chipinge", "region_ru": "\u041c\u0430\u043d\u0438\u043a\u0430\u043b\u0435\u043d\u0434", "region_uk": "\u041c\u0430\u043d\u0456\u043a\u0430\u043b\u0435\u043d\u0434", "region_en": "Manicaland", "alias": "chipinge", "country_alias": "zimbabwe"}, {"name_ru": "\u041c\u0443\u0442\u0430\u0440\u0435", "name_uk": "\u041c\u0443\u0442\u0430\u0440\u0435", "name_en": "Mutare", "region_ru": "\u041c\u0430\u043d\u0438\u043a\u0430\u043b\u0435\u043d\u0434", "region_uk": "\u041c\u0430\u043d\u0456\u043a\u0430\u043b\u0435\u043d\u0434", "region_en": "Manicaland", "alias": "mutare", "country_alias": "zimbabwe"}, {"name_ru": "\u041d\u044c\u044f\u043d\u0433\u0430", "name_uk": "\u041d\u044c\u044f\u043d\u0433\u0430", "name_en": "Nyanga", "region_ru": "\u041c\u0430\u043d\u0438\u043a\u0430\u043b\u0435\u043d\u0434", "region_uk": "\u041c\u0430\u043d\u0456\u043a\u0430\u043b\u0435\u043d\u0434", "region_en": "Manicaland", "alias": "nyanga", "country_alias": "zimbabwe"}, {"name_ru": "\u0420\u0443\u0441\u0430\u043f\u0435", "name_uk": "\u0420\u0443\u0441\u0430\u043f\u0435", "name_en": "Rusape", "region_ru": "\u041c\u0430\u043d\u0438\u043a\u0430\u043b\u0435\u043d\u0434", "region_uk": "\u041c\u0430\u043d\u0456\u043a\u0430\u043b\u0435\u043d\u0434", "region_en": "Manicaland", "alias": "rusape", "country_alias": "zimbabwe"}, {"name_ru": "\u0421\u0430\u043a\u0443\u0431\u0432\u0430", "name_uk": "\u0421\u0430\u043a\u0443\u0431\u0432\u0430", "name_en": "Sakubva", "region_ru": "\u041c\u0430\u043d\u0438\u043a\u0430\u043b\u0435\u043d\u0434", "region_uk": "\u041c\u0430\u043d\u0456\u043a\u0430\u043b\u0435\u043d\u0434", "region_en": "Manicaland", "alias": "sakubva", "country_alias": "zimbabwe"}, {"name_ru": "\u0427\u0438\u0440\u0435\u0434\u0437\u0438", "name_uk": "\u0427\u0456\u0440\u0435\u0434\u0437\u0456", "name_en": "Chiredzi", "region_ru": "\u041c\u0430\u0441\u0432\u0438\u043d\u0433\u043e", "region_uk": "\u041c\u0430\u0441\u0432\u0456\u043d\u0433\u043e", "region_en": "Masvingo", "alias": "chiredzi", "country_alias": "zimbabwe"}, {"name_ru": "\u0413\u0430\u0442\u044b", "name_uk": "\u0413\u0430\u0442\u0438", "name_en": "Gaths", "region_ru": "\u041c\u0430\u0441\u0432\u0438\u043d\u0433\u043e", "region_uk": "\u041c\u0430\u0441\u0432\u0456\u043d\u0433\u043e", "region_en": "Masvingo", "alias": "gaths", "country_alias": "zimbabwe"}, {"name_ru": "\u041c\u0430\u0441\u0432\u0438\u043d\u0433\u043e", "name_uk": "\u041c\u0430\u0441\u0432\u0456\u043d\u0433\u043e", "name_en": "Masvingo", "region_ru": "\u041c\u0430\u0441\u0432\u0438\u043d\u0433\u043e", "region_uk": "\u041c\u0430\u0441\u0432\u0456\u043d\u0433\u043e", "region_en": "Masvingo", "alias": "masvingo", "country_alias": "zimbabwe"}, {"name_ru": "\u0427\u0438\u0432\u0445\u0443", "name_uk": "\u0427\u0438\u0432\u0445\u0443", "name_en": "Chivhu", "region_ru": "\u041c\u0438\u0434\u043b\u0435\u043d\u0434\u0441", "region_uk": "\u041c\u0456\u0434\u043b\u0435\u043d\u0434\u0441", "region_en": "Midlands", "alias": "chivhu", "country_alias": "zimbabwe"}, {"name_ru": "\u0413\u0432\u0435\u0440\u0443", "name_uk": "\u0413\u0432\u0435\u0440\u0443", "name_en": "Gweru", "region_ru": "\u041c\u0438\u0434\u043b\u0435\u043d\u0434\u0441", "region_uk": "\u041c\u0456\u0434\u043b\u0435\u043d\u0434\u0441", "region_en": "Midlands", "alias": "gweru", "country_alias": "zimbabwe"}, {"name_ru": "\u041a\u0432\u0435\u043a\u0432\u0435", "name_uk": "\u043a\u0432\u0435\u043a\u0432\u0435", "name_en": "Kwekwe", "region_ru": "\u041c\u0438\u0434\u043b\u0435\u043d\u0434\u0441", "region_uk": "\u041c\u0456\u0434\u043b\u0435\u043d\u0434\u0441", "region_en": "Midlands", "alias": "kwekwe", "country_alias": "zimbabwe"}, {"name_ru": "\u041c\u0432\u0443\u043c\u0430", "name_uk": "\u041c\u0432\u0443\u043c\u0430", "name_en": "Mvuma", "region_ru": "\u041c\u0438\u0434\u043b\u0435\u043d\u0434\u0441", "region_uk": "\u041c\u0456\u0434\u043b\u0435\u043d\u0434\u0441", "region_en": "Midlands", "alias": "mvuma", "country_alias": "zimbabwe"}, {"name_ru": "\u0420\u0435\u0434\u043a\u043b\u0438\u0444\u0444", "name_uk": "\u0420\u0435\u0434\u043a\u043b\u0456\u0444\u0444", "name_en": "Redcliffe", "region_ru": "\u041c\u0438\u0434\u043b\u0435\u043d\u0434\u0441", "region_uk": "\u041c\u0456\u0434\u043b\u0435\u043d\u0434\u0441", "region_en": "Midlands", "alias": "redcliffe", "country_alias": "zimbabwe"}, {"name_ru": "\u0428\u0443\u0440\u0443\u0433\u0432\u0438", "name_uk": "\u0428\u0443\u0440\u0443\u0433\u0432\u0456", "name_en": "Shurugwi", "region_ru": "\u041c\u0438\u0434\u043b\u0435\u043d\u0434\u0441", "region_uk": "\u041c\u0456\u0434\u043b\u0435\u043d\u0434\u0441", "region_en": "Midlands", "alias": "shurugwi", "country_alias": "zimbabwe"}, {"name_ru": "\u0417\u0432\u0438\u0448\u0430\u0432\u0430\u043d\u0435", "name_uk": "\u0417\u0432\u0456\u0448\u0430\u0432\u0430\u043d\u0435", "name_en": "Zvishavane", "region_ru": "\u041c\u0438\u0434\u043b\u0435\u043d\u0434\u0441", "region_uk": "\u041c\u0456\u0434\u043b\u0435\u043d\u0434\u0441", "region_en": "Midlands", "alias": "zvishavane", "country_alias": "zimbabwe"}]}